ic_parent_api/__init__.py
ic_parent_api/base.py
ic_parent_api/ic_api_client.py
ic_parent_api/infinitecampus.py
ic_parent_api/errors/__init__.py
ic_parent_api/errors/ic_error.py
ic_parent_api/models/__init__.py
ic_parent_api/models/assignment.py
ic_parent_api/models/base.py
ic_parent_api/models/course.py
ic_parent_api/models/enrollment.py
ic_parent_api/models/placement.py
ic_parent_api/models/scheduleday.py
ic_parent_api/models/student.py
ic_parent_api/models/term.py
ic_parent_api-0.0.16.dist-info/LICENSE
ic_parent_api-0.0.16.dist-info/METADATA
ic_parent_api-0.0.16.dist-info/WHEEL
ic_parent_api-0.0.16.dist-info/top_level.txt
ic_parent_api-0.0.16.dist-info/RECORD
